langsec/__init__.py
langsec/config.py
langsec/core/__init__.py
langsec/core/security.py
langsec/exceptions/__init__.py
langsec/exceptions/errors.py
langsec/schema/__init__.py
langsec/schema/defaults.py
langsec/schema/security_schema.py
langsec/schema/sql/__init__.py
langsec/schema/sql/connectors.py
langsec/schema/sql/enums.py
langsec/validators/__init__.py
langsec/validators/aggregation.py
langsec/validators/base.py
langsec/validators/column.py
langsec/validators/injection.py
langsec/validators/join.py
langsec/validators/query.py
langsec/validators/subquery.py
langsec/validators/table.py
langsec-0.0.1.dist-info/LICENSE
langsec-0.0.1.dist-info/METADATA
langsec-0.0.1.dist-info/WHEEL
langsec-0.0.1.dist-info/top_level.txt
langsec-0.0.1.dist-info/RECORD
