Metadata-Version: 2.1
Name: langsec
Version: 0.0.1
Summary: Security framework for LLM-generated SQL queries
Home-page: https://github.com/langsec-ai/langsec
Author: LangSec
Author-email: dev@lang-sec.com
Classifier: Development Status :: 3 - Alpha
Classifier: Intended Audience :: Developers
Classifier: License :: OSI Approved :: Apache Software License
Classifier: Programming Language :: Python :: 3
Classifier: Programming Language :: Python :: 3.8
Classifier: Programming Language :: Python :: 3.9
Classifier: Programming Language :: Python :: 3.10
Classifier: Programming Language :: Python :: 3.11
Classifier: Programming Language :: Python :: 3.12
Requires-Python: >=3.8
License-File: LICENSE
Requires-Dist: sqlglot >=11.5.0
Requires-Dist: pydantic >=2.0.0
Requires-Dist: typing-extensions >=4.0.0
Provides-Extra: dev
Requires-Dist: pytest >=7.0.0 ; extra == 'dev'
Requires-Dist: black >=23.0.0 ; extra == 'dev'
Requires-Dist: mypy >=1.0.0 ; extra == 'dev'
Requires-Dist: isort >=5.0.0 ; extra == 'dev'
